htmltest/__init__.py
htmltest/html.py
htmltester-0.0.6.dist-info/METADATA
htmltester-0.0.6.dist-info/WHEEL
htmltester-0.0.6.dist-info/entry_points.txt
htmltester-0.0.6.dist-info/top_level.txt
htmltester-0.0.6.dist-info/RECORD
