Metadata-Version: 2.4
Name: htmltester
Version: 0.0.6
Summary: Open html files in your browser quickly.
Author: Erri4
Project-URL: Homepage, https://github.com/erri4/htmltest
Project-URL: Bug Tracker, https://github.com/erri4/htmltest/issues
Classifier: License :: Other/Proprietary License
Requires-Python: >=3.8
Requires-Dist: flask
